livesrt/__init__.py
livesrt/__main__.py
livesrt/async_tools.py
livesrt/cli.py
livesrt/config_template.py
livesrt/constants.py
livesrt/containers.py
livesrt/errors.py
livesrt/services.py
livesrt/transcribe/__init__.py
livesrt/transcribe/audio_sources/__init__.py
livesrt/transcribe/audio_sources/mic.py
livesrt/transcribe/audio_sources/replay_file.py
livesrt/transcribe/base.py
livesrt/transcribe/transcripters/__init__.py
livesrt/transcribe/transcripters/aai.py
livesrt/transcribe/transcripters/elevenlabs.py
livesrt/transcribe/transcripters/speechmatics.py
livesrt/translate/__init__.py
livesrt/translate/base.py
livesrt/translate/local_llm.py
livesrt/translate/remote_llm.py
livesrt/tui.py
livesrt/utils.py
livesrt-0.1.1.dist-info/WHEEL
livesrt-0.1.1.dist-info/entry_points.txt
livesrt-0.1.1.dist-info/METADATA
livesrt-0.1.1.dist-info/RECORD
