Metadata-Version: 2.3
Name: livesrt
Version: 0.1.1
Summary: Live subtitles for your life
Author: Rémy Sanchez
Author-email: Rémy Sanchez <remy.sanchez@hyperthese.net>
Requires-Dist: rich
Requires-Dist: rich-click
Requires-Dist: click
Requires-Dist: httpx
Requires-Dist: pyyaml
Requires-Dist: keyring
Requires-Dist: pwinput
Requires-Dist: pyaudio
Requires-Dist: websockets
Requires-Dist: pydantic
Requires-Dist: tenacity
Requires-Dist: huggingface-hub~=1.2.1
Requires-Dist: llama-cpp-python~=0.3.16
Requires-Dist: textual>=6.8.0
Requires-Dist: dependency-injector>=4.48.3
Requires-Python: >=3.12
